{
  "title": "Social Security Full Retirement Benefit 2025 \u2013 Benefits Amount & Eligibility Check",
  "publication_date": "2025-04-18T22:05:00+05:30",
  "summary": "The Social Security Administration announces changes to retirement benefits for 2025, including a 2.5% COLA adjustment. Eligibility requires 35 years of work history and 40 labor credits. Maximum benefits are available to those with 35 years of maximum wages and delayed retirement. The program provides retirement income, disability assistance, and survivor benefits to eligible Americans aged 62 and above.",
  "content": "With its retirement income, disability help, and survivor benefits, Social Security is an essential financial lifeline for countless Americans. Depending on their retirement age, earnings history, and other variables, many recipients expect to receive the Social Security Full Retirement Benefit 2025.\n\nA Social Security retirement payout in 2025 requires individuals to fulfill certain requirements, such as 35 years of maximum wages and postponed retirement. The United States Social Security Administration administers these payments to reduce financial burden for residents.\n\nAll retirees, disabled individuals, and their eligible dependents can receive Social Security benefits. Due to COLA 2025, Social Security payments have undergone modifications, with a 2.5% adjustment rate, lower than 2024's rate.\n\nThe main insurance amount (PIA) is determined using the highest 35 years of earnings, adjusted for inflation. For those under Full Retirement Age (FRA), earnings exceeding $21,240 in 2025 may temporarily reduce benefits, though no earnings cap exists after reaching FRA.\n\nApplicants must complete online forms through the SSA or VA website. It's important to note that specific benefit amounts remain speculative until officially announced by the SSA. Recipients should verify information through the official SSA website before submitting applications.",
  "category": "Business",
  "tags": [
    "social security",
    "retirement",
    "pension",
    "COLA",
    "government benefits",
    "financial planning",
    "SSA"
  ],
  "location": "United States",
  "source": {
    "title": "Social Security Full Retirement Benefit 2025 \u2013 Benefits Amount & Eligibility Check",
    "publication_date": 1744974300,
    "content": [
      {
        "title": "Social Security Full Retirement Benefit 2025 - Benefits Amount & Eligibility Check",
        "publication_date": "2025-04-18T22:05:00+05:30",
        "content": "With its retirement income, disability help, and survivor benefits, Social Security is an essential financial lifeline for countless Americans. Depending on their retirement age, earnings history, and other variables, many recipients expect to receive theSocial Security Full Retirement Benefit 2025.\n\nA Social Security retirement payout in 2025 is a wonderful idea, but only individuals who fulfil certain requirements, such as 35 years of maximum wages and postponed retirement, can get it. You may ensure a more pleasant future by knowing how benefits are determined, taking action to increase your income, and carefully arranging your retirement plan. To maximise your Social Security payments, take proactive measures and seek advice from a financial professional.\n\nIt is important for you to check theFull Social Security Benefit Eligibility Criteria 2025and then receive the benefits in your account. It is important for you to check the$2831 Social Security Benefit April 2025which will be credited in your bank account.\n\nThe United States Social Security Administration is the agency that pays out money to its residents to lessen their financial burden. For Americans who are sixty-two years of age or over, Social Security is paid by the Social Security Administration (SSA). People who want to improve their financial situation can profit fromSocial Security Full Retirement Benefit 2025, which is paid to people who have been employed for 35 years and accrued more than 40 labour credits.\n\nAll pensioners who have been adolescents and their partners who have been disabled in some way, although they have descendants, will get their Social Security benefits. Due to COLA 2025, Social Security payments have undergone several modifications as of the new year. While the adjustment was less than that of 2024, the COLA rate for 2025 was 2.5%.\n\nCheck theFull Social Security Benefit Eligibility Criteria 2025through the listed points.\n\nTo be eligible for the benefits of the program, individuals must fill out the online form on the SSA or VA website. Afterward, they must proceed with the subsequent tasks.\n\nFor their advantages, one might confirm the needed payment dates:\n\nIt is crucial to remember that the Social Security Full Retirement Benefit under discussion are entirely speculative, and SSA has not yet released an official statement about the exact amount. Before submitting their grant applications, prospective candidates are advised to rely on accurate and up-to-date information and to confirm the information on the official SSA website.\n\nYour main insurance amount (PIA) is determined by Social Security using your greatest 35 years of earnings, adjusted for inflation. At FRA, your benefit is determined by your PIA.\n\nYes, however, if your wages surpass the yearly cap ($21,240 in 2025) and you haven\u2019t hit FRA, your benefits can be temporarily lowered. There is no cap on earnings after the FRA is reached.\n\nIf your payment doesn\u2019t show up on the expected date, make sure to reach out to the Social Security Administration right away. Inaccurate address updates or financial information might cause problems.\n\nIt is a pension made for retired people whose spouses have disabilities.\n\nSoniya Sahota is Finance professional with MBA Finance degree from University Of London, she completed her Master\u2019s in \u201915. Now she is working as a senior content editor at D News, Finance, Education & Sports News portal.\n\nComment\n\nSave my name, email, and website in this browser for the next time I comment.\n\nContact Us-Disclamer-Privacy Policy"
      },
      {
        "title": "Social Security Full Retirement Benefit 2025 - Benefits Amount & Eligibility Check",
        "author": "Unknown Author",
        "publication_date": "2025-04-18T22:05:00+05:30"
      }
    ],
    "authors": [],
    "source": "dpradhanbjp.com",
    "image_url": "https://dpradhanbjp.com/wp-content/uploads/2025/04/Social-Security-Full-Retirement-Benefit-2025.jpg",
    "url": "https://dpradhanbjp.com/social-security-full-retirement-benefit-2025/"
  },
  "markdown_content": "## Social Security Benefits Overview\\nWith its retirement income, disability help, and survivor benefits, Social Security is an essential financial lifeline for countless Americans. Depending on their retirement age, earnings history, and other variables, many recipients expect to receive the Social Security Full Retirement Benefit 2025.\\n\\n## Eligibility Requirements\\nA Social Security retirement payout in 2025 requires individuals to fulfill certain requirements, such as 35 years of maximum wages and postponed retirement. The United States Social Security Administration administers these payments to reduce financial burden for residents.\\n\\n## Benefit Recipients and COLA Adjustments\\nAll retirees, disabled individuals, and their eligible dependents can receive Social Security benefits. Due to COLA 2025, Social Security payments have undergone modifications, with a 2.5% adjustment rate, lower than 2024's rate.\\n\\n## Benefit Calculations\\nThe main insurance amount (PIA) is determined using the highest 35 years of earnings, adjusted for inflation. For those under Full Retirement Age (FRA), earnings exceeding $21,240 in 2025 may temporarily reduce benefits, though no earnings cap exists after reaching FRA.\\n\\n## Application Process\\nApplicants must complete online forms through the SSA or VA website. It's important to note that specific benefit amounts remain speculative until officially announced by the SSA. Recipients should verify information through the official SSA website before submitting applications."
}